aviutl2_api/__init__.py
aviutl2_api/cli.py
aviutl2_api/json_converter.py
aviutl2_api/parser.py
aviutl2_api/presets.py
aviutl2_api/serializer.py
aviutl2_api/models/__init__.py
aviutl2_api/models/project.py
aviutl2_api/models/values.py
aviutl2_api/renderer/__init__.py
aviutl2_api/renderer/blend.py
aviutl2_api/renderer/canvas.py
aviutl2_api/renderer/core.py
aviutl2_api/renderer/interpolation.py
aviutl2_api/renderer/transform.py
aviutl2_api/renderer/content/__init__.py
aviutl2_api/renderer/content/base.py
aviutl2_api/renderer/content/image.py
aviutl2_api/renderer/content/shape.py
aviutl2_api/renderer/content/text.py
aviutl2_api/renderer/content/video.py
aviutl2_api/renderer/filters/__init__.py
aviutl2_api/renderer/filters/base.py
aviutl2_api/renderer/filters/blur.py
aviutl2_api/renderer/filters/border.py
aviutl2_api/renderer/filters/glow.py
aviutl2_api/renderer/filters/shadow.py
aviutl2_api-0.1.4.dist-info/METADATA
aviutl2_api-0.1.4.dist-info/WHEEL
aviutl2_api-0.1.4.dist-info/entry_points.txt
aviutl2_api-0.1.4.dist-info/licenses/LICENSE
aviutl2_api-0.1.4.dist-info/RECORD
