Metadata-Version: 2.4
Name: aviutl2-api
Version: 0.1.4
Summary: Python API for AviUtl ver.2 project files (.aup2)
Author: swatanabe
License-Expression: MIT
License-File: LICENSE
Keywords: automation,aviutl,video-editing
Classifier: Development Status :: 3 - Alpha
Classifier: Intended Audience :: Developers
Classifier: License :: OSI Approved :: MIT License
Classifier: Programming Language :: Python :: 3
Classifier: Programming Language :: Python :: 3.10
Classifier: Programming Language :: Python :: 3.11
Classifier: Programming Language :: Python :: 3.12
Requires-Python: >=3.10
Requires-Dist: click>=8.0
Requires-Dist: numpy>=1.24
Requires-Dist: opencv-python>=4.8
Requires-Dist: pillow>=10.0
Provides-Extra: dev
Requires-Dist: mypy>=1.0; extra == 'dev'
Requires-Dist: pytest>=7.0; extra == 'dev'
Requires-Dist: ruff>=0.1; extra == 'dev'
